ylapp/__init__.py
ylapp/cli.py
ylapp/commands/__init__.py
ylapp/commands/help.py
ylapp/commands/init_ai_app_project.py
ylapp/commands/dto_scan/__init__.py
ylapp/commands/dto_scan/gdto_scan.py
ylapp/commands/dto_scan/verify_logic.py
ylapp/core/command.py
ylapp/core/config.py
ylapp/core/io.py
ylapp/core/logger.py
ylapp/core/registry.py
ylapp/core/repl.py
ylapp/core/router.py
ylapp_flutter_devkit-0.0.3.dist-info/licenses/LICENSE
ylapp_flutter_devkit-0.0.3.dist-info/METADATA
ylapp_flutter_devkit-0.0.3.dist-info/WHEEL
ylapp_flutter_devkit-0.0.3.dist-info/entry_points.txt
ylapp_flutter_devkit-0.0.3.dist-info/top_level.txt
ylapp_flutter_devkit-0.0.3.dist-info/RECORD
